MANIFEST.in
setup.py
django_user_profile.egg-info/PKG-INFO
django_user_profile.egg-info/SOURCES.txt
django_user_profile.egg-info/dependency_links.txt
django_user_profile.egg-info/not-zip-safe
django_user_profile.egg-info/top_level.txt
user_profile/__init__.py
user_profile/forms.py
user_profile/models.py
user_profile/tests.py
user_profile/urls.py
user_profile/views.py
user_profile/templates/user_profile/change.html